[
  {
    "rank": 1,
    "uid": "b6ea05f7-28b2-4c81-8adc-8afce3b53c64",
    "username": "F1Fan1997",
    "wagered": 15464.692235000017,
    "weightedWagered": 12156.524426000016
  },
  {
    "rank": 2,
    "uid": "d57ed2f5-814a-42cd-b347-0675b4dc3dcd",
    "username": "slicksloth97",
    "wagered": 16178.146543600045,
    "weightedWagered": 7475.599393599984
  },
  {
    "rank": 3,
    "uid": "8ec037ae-a2b4-4266-8239-c31d9c95ef04",
    "username": "WhiteRabbit420",
    "wagered": 5290.559999999822,
    "weightedWagered": 1702.1600000000599
  },
  {
    "rank": 4,
    "uid": "9ed55e72-3faa-4fbe-bf35-1291fb365c07",
    "username": "MrBrizz",
    "wagered": 1269.9417360999996,
    "weightedWagered": 1193.4314021500002
  },
  {
    "rank": 5,
    "uid": "a4fd519d-4cb0-478c-b08f-d062a6755b15",
    "username": "fliptheswitchop",
    "wagered": 3447.632594700012,
    "weightedWagered": 1116.40790470001
  },
  {
    "rank": 6,
    "uid": "4c3b9e0e-cbed-48b6-9286-414dbe49ddd2",
    "username": "tremor11",
    "wagered": 1094.4916825999999,
    "weightedWagered": 1094.4916825999999
  },
  {
    "rank": 7,
    "uid": "99fe2581-2089-4534-992a-50ab22e7313d",
    "username": "Rusi46",
    "wagered": 2899.219999999994,
    "weightedWagered": 923.7520000000012
  },
  {
    "rank": 8,
    "uid": "0df0959d-7648-41f4-bccc-349021c9d165",
    "username": "liq543",
    "wagered": 344.4317668999992,
    "weightedWagered": 325.3477279999992
  },
  {
    "rank": 9,
    "uid": "87588145-0b0f-4d7e-923d-e46aa9001736",
    "username": "1who1",
    "wagered": 273.1762489000003,
    "weightedWagered": 273.1762489000003
  },
  {
    "rank": 10,
    "uid": "16a098a3-be65-45a4-bcb5-72716ba74664",
    "username": "Gabtoupin",
    "wagered": 179.56732560000017,
    "weightedWagered": 178.7811072000002
  }
]