[
  {
    "rank": 1,
    "uid": "d0d74e0f-6c75-4d74-a7cd-4d0a60dac400",
    "username": "Zopipa",
    "wagered": 9597.999999997264,
    "weightedWagered": 9027.599999996792
  },
  {
    "rank": 2,
    "uid": "0dbf266b-1680-4057-86be-22ac6470842e",
    "username": "hotrunners",
    "wagered": 9964.11999999664,
    "weightedWagered": 7981.399999997153
  },
  {
    "rank": 3,
    "uid": "ee7092eb-12c5-4187-89c2-6a970abe4647",
    "username": "MacMacman",
    "wagered": 12252.99999999922,
    "weightedWagered": 7655.499999999153
  },
  {
    "rank": 4,
    "uid": "16a098a3-be65-45a4-bcb5-72716ba74664",
    "username": "Gabtoupin",
    "wagered": 7015.039692931961,
    "weightedWagered": 6860.415681177249
  },
  {
    "rank": 5,
    "uid": "a4fd519d-4cb0-478c-b08f-d062a6755b15",
    "username": "fliptheswitchop",
    "wagered": 21222.8945640404,
    "weightedWagered": 6218.497609816215
  },
  {
    "rank": 6,
    "uid": "79c0ff7b-dde8-4998-beea-4f3bb4e61c3b",
    "username": "flipmiller",
    "wagered": 6334.914056337187,
    "weightedWagered": 5992.303659857626
  },
  {
    "rank": 7,
    "uid": "8f79fff3-052e-4692-9d4f-ae3a36931d21",
    "username": "Jameskobi10",
    "wagered": 3662.0351020253347,
    "weightedWagered": 3052.199536284663
  },
  {
    "rank": 8,
    "uid": "54ba7542-df9e-486e-9491-3c3e124875c1",
    "username": "gdigital87",
    "wagered": 1717.4,
    "weightedWagered": 1717.4
  },
  {
    "rank": 9,
    "uid": "b90bde1d-5c60-45af-930b-d2d1f15cc1a6",
    "username": "smithloic2",
    "wagered": 1567.7050848092426,
    "weightedWagered": 1567.7050848092426
  },
  {
    "rank": 10,
    "uid": "b6ea05f7-28b2-4c81-8adc-8afce3b53c64",
    "username": "F1Fan1997",
    "wagered": 1536.9307505916709,
    "weightedWagered": 1441.4763327224532
  }
]