[
  {
    "rank": 1,
    "uid": "9639491d-3e54-47fa-a116-0294790dbe9a",
    "username": "Foxxy123",
    "wagered": 170311.44804934482,
    "weightedWagered": 165586.99241405496
  },
  {
    "rank": 2,
    "uid": "16a098a3-be65-45a4-bcb5-72716ba74664",
    "username": "Gabtoupin",
    "wagered": 99645.66670549738,
    "weightedWagered": 99639.84655081236
  },
  {
    "rank": 3,
    "uid": "0dbf266b-1680-4057-86be-22ac6470842e",
    "username": "hotrunners",
    "wagered": 52298.770897257054,
    "weightedWagered": 47984.850897256445
  },
  {
    "rank": 4,
    "uid": "8f79fff3-052e-4692-9d4f-ae3a36931d21",
    "username": "Jameskobi10",
    "wagered": 48535.96060100375,
    "weightedWagered": 43766.34938503776
  },
  {
    "rank": 5,
    "uid": "fb2475ce-e59f-4fd1-8edb-17b3e743423e",
    "username": "WCDegen",
    "wagered": 71422.828565555,
    "weightedWagered": 29917.248312539774
  },
  {
    "rank": 6,
    "uid": "d57ed2f5-814a-42cd-b347-0675b4dc3dcd",
    "username": "slicksloth97",
    "wagered": 26835.876098760506,
    "weightedWagered": 18487.94202298346
  },
  {
    "rank": 7,
    "uid": "b6ea05f7-28b2-4c81-8adc-8afce3b53c64",
    "username": "F1Fan1997",
    "wagered": 17751.28920199674,
    "weightedWagered": 12682.13407181645
  },
  {
    "rank": 8,
    "uid": "ec5371fd-0e98-40d0-897f-e389773c0684",
    "username": "Meepflips",
    "wagered": 10337.386627684473,
    "weightedWagered": 8929.615224108953
  },
  {
    "rank": 9,
    "uid": "79c0ff7b-dde8-4998-beea-4f3bb4e61c3b",
    "username": "flipmiller",
    "wagered": 8394.144951153568,
    "weightedWagered": 8091.844065637355
  },
  {
    "rank": 10,
    "uid": "7f921117-01a7-4d12-9605-3e33f03c14de",
    "username": "Alxxwilson",
    "wagered": 6926.452384466946,
    "weightedWagered": 6908.406153031106
  }
]