[
  {
    "rank": 1,
    "uid": "ee7092eb-12c5-4187-89c2-6a970abe4647",
    "username": "MacMacman",
    "wagered": 35689.39999999968,
    "weightedWagered": 35402.89999999968
  },
  {
    "rank": 2,
    "uid": "d0d74e0f-6c75-4d74-a7cd-4d0a60dac400",
    "username": "Zopipa",
    "wagered": 23612.33000002633,
    "weightedWagered": 22289.930000025972
  },
  {
    "rank": 3,
    "uid": "16a098a3-be65-45a4-bcb5-72716ba74664",
    "username": "Gabtoupin",
    "wagered": 21049.54994353795,
    "weightedWagered": 20995.02756475162
  },
  {
    "rank": 4,
    "uid": "a4fd519d-4cb0-478c-b08f-d062a6755b15",
    "username": "fliptheswitchop",
    "wagered": 25385.207064037866,
    "weightedWagered": 19075.10585270838
  },
  {
    "rank": 5,
    "uid": "b6ea05f7-28b2-4c81-8adc-8afce3b53c64",
    "username": "F1Fan1997",
    "wagered": 16556.431888192514,
    "weightedWagered": 13832.423315768105
  },
  {
    "rank": 6,
    "uid": "b90bde1d-5c60-45af-930b-d2d1f15cc1a6",
    "username": "smithloic2",
    "wagered": 11703.086262807989,
    "weightedWagered": 11008.890060446789
  },
  {
    "rank": 7,
    "uid": "d57ed2f5-814a-42cd-b347-0675b4dc3dcd",
    "username": "slicksloth97",
    "wagered": 21396.43999999962,
    "weightedWagered": 10770.541999999981
  },
  {
    "rank": 8,
    "uid": "0dbf266b-1680-4057-86be-22ac6470842e",
    "username": "hotrunners",
    "wagered": 9110.950000000665,
    "weightedWagered": 6471.399999998985
  },
  {
    "rank": 9,
    "uid": "8f79fff3-052e-4692-9d4f-ae3a36931d21",
    "username": "Jameskobi10",
    "wagered": 5500.800496716825,
    "weightedWagered": 5469.64026373141
  },
  {
    "rank": 10,
    "uid": "79c0ff7b-dde8-4998-beea-4f3bb4e61c3b",
    "username": "flipmiller",
    "wagered": 5429.097245396278,
    "weightedWagered": 5196.254411594185
  }
]