[
  {
    "rank": 1,
    "uid": "9639491d-3e54-47fa-a116-0294790dbe9a",
    "username": "Foxxy123",
    "wagered": 33973.59999999855,
    "weightedWagered": 33314.599999998696
  },
  {
    "rank": 2,
    "uid": "ec5371fd-0e98-40d0-897f-e389773c0684",
    "username": "Meepflips",
    "wagered": 39091.01651555208,
    "weightedWagered": 28613.749227434277
  },
  {
    "rank": 3,
    "uid": "8f79fff3-052e-4692-9d4f-ae3a36931d21",
    "username": "Jameskobi10",
    "wagered": 24486.727140167277,
    "weightedWagered": 22593.53121554084
  },
  {
    "rank": 4,
    "uid": "fb2475ce-e59f-4fd1-8edb-17b3e743423e",
    "username": "WCDegen",
    "wagered": 45550.46029716376,
    "weightedWagered": 18147.849515584126
  },
  {
    "rank": 5,
    "uid": "9ed55e72-3faa-4fbe-bf35-1291fb365c07",
    "username": "MrBrizz",
    "wagered": 15889.911843836166,
    "weightedWagered": 15817.177119434804
  },
  {
    "rank": 6,
    "uid": "79c0ff7b-dde8-4998-beea-4f3bb4e61c3b",
    "username": "flipmiller",
    "wagered": 16536.716016036233,
    "weightedWagered": 15594.025350527643
  },
  {
    "rank": 7,
    "uid": "d6a0ca4d-0f66-47f2-a05b-464abdaa808b",
    "username": "ProxyWoxy",
    "wagered": 10983.934782742663,
    "weightedWagered": 8979.28486321377
  },
  {
    "rank": 8,
    "uid": "68465667-21bf-4cd7-b674-dce075b60755",
    "username": "Laztheraz",
    "wagered": 6768.090000000213,
    "weightedWagered": 6253.3150000002115
  },
  {
    "rank": 9,
    "uid": "dc3dc9eb-c862-4241-a546-8fb85437a0d3",
    "username": "Jakaflip",
    "wagered": 6103.45831090078,
    "weightedWagered": 5869.491113481887
  },
  {
    "rank": 10,
    "uid": "b6ea05f7-28b2-4c81-8adc-8afce3b53c64",
    "username": "F1Fan1997",
    "wagered": 4292.813068519437,
    "weightedWagered": 3933.1187245154592
  }
]