[
  {
    "rank": 1,
    "uid": "d57ed2f5-814a-42cd-b347-0675b4dc3dcd",
    "username": "slicksloth97",
    "wagered": 244471.393511591,
    "weightedWagered": 121923.54963159867
  },
  {
    "rank": 2,
    "uid": "b6ea05f7-28b2-4c81-8adc-8afce3b53c64",
    "username": "F1Fan1997",
    "wagered": 26408.8819106006,
    "weightedWagered": 20400.9734233186
  },
  {
    "rank": 3,
    "uid": "4c3b9e0e-cbed-48b6-9286-414dbe49ddd2",
    "username": "tremor11",
    "wagered": 8959.42836269999,
    "weightedWagered": 8782.222289299796
  },
  {
    "rank": 4,
    "uid": "f1221846-8619-403a-85f1-f867a82967d2",
    "username": "nebdubz",
    "wagered": 5536.600459700085,
    "weightedWagered": 5508.2822432500825
  },
  {
    "rank": 5,
    "uid": "99fe2581-2089-4534-992a-50ab22e7313d",
    "username": "Rusi46",
    "wagered": 12282.999999999309,
    "weightedWagered": 3237.3100000005657
  },
  {
    "rank": 6,
    "uid": "a4fd519d-4cb0-478c-b08f-d062a6755b15",
    "username": "fliptheswitchop",
    "wagered": 7796.069545299978,
    "weightedWagered": 2601.060499300069
  },
  {
    "rank": 7,
    "uid": "9ed55e72-3faa-4fbe-bf35-1291fb365c07",
    "username": "MrBrizz",
    "wagered": 2550.0517436999967,
    "weightedWagered": 2445.011104649994
  },
  {
    "rank": 8,
    "uid": "8ec037ae-a2b4-4266-8239-c31d9c95ef04",
    "username": "WhiteRabbit420",
    "wagered": 5332.252800002973,
    "weightedWagered": 1715.7327999998229
  },
  {
    "rank": 9,
    "uid": "87588145-0b0f-4d7e-923d-e46aa9001736",
    "username": "1who1",
    "wagered": 840.677946900019,
    "weightedWagered": 651.6712669000048
  },
  {
    "rank": 10,
    "uid": "0df0959d-7648-41f4-bccc-349021c9d165",
    "username": "liq543",
    "wagered": 344.431766899998,
    "weightedWagered": 325.347727999998
  }
]