{
  "leaderboard_type": "multiplier",
  "period": {
    "start_date": "2025-08-01T00:00:00+00:00",
    "end_date": "2025-08-31T23:59:59+00:00",
    "start_timestamp": 1754006400,
    "end_timestamp": 1756684799
  },
  "last_updated": "2025-08-30T06:42:08.549699+00:00",
  "last_updated_timestamp": 1756536128,
  "entries": [
    {
      "rank": 1,
      "username": "GemEventual123",
      "multiplier": 1372.8,
      "game": "Wanted Dead or a Wild",
      "game_identifier": null,
      "wagered": 0.7229,
      "payout": 992.39712,
      "prize": 75
    },
    {
      "rank": 2,
      "username": "Laztheraz",
      "multiplier": 1304.857142857143,
      "game": "Mental 2",
      "game_identifier": null,
      "wagered": 0.28,
      "payout": 365.36,
      "prize": 50
    },
    {
      "rank": 3,
      "username": "enimatekkkk",
      "multiplier": 1000,
      "game": "Plinko",
      "game_identifier": null,
      "wagered": 0.46527999999999997,
      "payout": 465.28,
      "prize": 25
    },
    {
      "rank": 4,
      "username": "MaxWeen92",
      "multiplier": 845.9999999999999,
      "game": "Wanted Dead or a Wild",
      "game_identifier": null,
      "wagered": 0.58152,
      "payout": 491.96592,
      "prize": 10
    },
    {
      "rank": 5,
      "username": "liq543",
      "multiplier": 828.7,
      "game": "Dig It!",
      "game_identifier": null,
      "wagered": 0.21725999999999998,
      "payout": 180.043362,
      "prize": 5
    }
  ]
}