[
  {
    "rank": 1,
    "uid": "16a098a3-be65-45a4-bcb5-72716ba74664",
    "username": "Gabtoupin",
    "wagered": 20460.483704351365,
    "weightedWagered": 20415.730448622548
  },
  {
    "rank": 2,
    "uid": "d0d74e0f-6c75-4d74-a7cd-4d0a60dac400",
    "username": "Zopipa",
    "wagered": 20137.730000002048,
    "weightedWagered": 18906.330000000897
  },
  {
    "rank": 3,
    "uid": "b6ea05f7-28b2-4c81-8adc-8afce3b53c64",
    "username": "F1Fan1997",
    "wagered": 15821.419294226105,
    "weightedWagered": 13218.544856106759
  },
  {
    "rank": 4,
    "uid": "d57ed2f5-814a-42cd-b347-0675b4dc3dcd",
    "username": "slicksloth97",
    "wagered": 19160.359999999833,
    "weightedWagered": 10301.262000000102
  },
  {
    "rank": 5,
    "uid": "a4fd519d-4cb0-478c-b08f-d062a6755b15",
    "username": "fliptheswitchop",
    "wagered": 15526.158155986917,
    "weightedWagered": 10134.906149981762
  },
  {
    "rank": 6,
    "uid": "b90bde1d-5c60-45af-930b-d2d1f15cc1a6",
    "username": "smithloic2",
    "wagered": 3772.433365633307,
    "weightedWagered": 3651.3959441445763
  },
  {
    "rank": 7,
    "uid": "8f79fff3-052e-4692-9d4f-ae3a36931d21",
    "username": "Jameskobi10",
    "wagered": 2571.569881670961,
    "weightedWagered": 2571.569881670961
  },
  {
    "rank": 8,
    "uid": "07ae10b6-80ee-469e-9741-bd7189312685",
    "username": "TheRealMrClean",
    "wagered": 3604.6705199173475,
    "weightedWagered": 2232.35089944414
  },
  {
    "rank": 9,
    "uid": "79c0ff7b-dde8-4998-beea-4f3bb4e61c3b",
    "username": "flipmiller",
    "wagered": 1662.8034262717163,
    "weightedWagered": 1597.71340849273
  },
  {
    "rank": 10,
    "uid": "ee7092eb-12c5-4187-89c2-6a970abe4647",
    "username": "MacMacman",
    "wagered": 1340.9000000000235,
    "weightedWagered": 1261.650000000023
  }
]