[
  {
    "rank": 1,
    "uid": "9639491d-3e54-47fa-a116-0294790dbe9a",
    "username": "Foxxy123",
    "wagered": 33973.5999999964,
    "weightedWagered": 33314.59999999341
  },
  {
    "rank": 2,
    "uid": "ec5371fd-0e98-40d0-897f-e389773c0684",
    "username": "Meepflips",
    "wagered": 39091.016515552,
    "weightedWagered": 28613.7492274345
  },
  {
    "rank": 3,
    "uid": "8f79fff3-052e-4692-9d4f-ae3a36931d21",
    "username": "Jameskobi10",
    "wagered": 24486.72714016701,
    "weightedWagered": 22593.531215540686
  },
  {
    "rank": 4,
    "uid": "fb2475ce-e59f-4fd1-8edb-17b3e743423e",
    "username": "WCDegen",
    "wagered": 45550.46029716375,
    "weightedWagered": 18147.84951558372
  },
  {
    "rank": 5,
    "uid": "9ed55e72-3faa-4fbe-bf35-1291fb365c07",
    "username": "MrBrizz",
    "wagered": 15889.911843835882,
    "weightedWagered": 15817.177119434522
  },
  {
    "rank": 6,
    "uid": "79c0ff7b-dde8-4998-beea-4f3bb4e61c3b",
    "username": "flipmiller",
    "wagered": 16536.716016036087,
    "weightedWagered": 15594.025350527285
  },
  {
    "rank": 7,
    "uid": "d6a0ca4d-0f66-47f2-a05b-464abdaa808b",
    "username": "ProxyWoxy",
    "wagered": 10983.934782742568,
    "weightedWagered": 8979.284863213814
  },
  {
    "rank": 8,
    "uid": "68465667-21bf-4cd7-b674-dce075b60755",
    "username": "Laztheraz",
    "wagered": 6768.089999999634,
    "weightedWagered": 6253.314999999632
  },
  {
    "rank": 9,
    "uid": "dc3dc9eb-c862-4241-a546-8fb85437a0d3",
    "username": "Jakaflip",
    "wagered": 6103.458310900851,
    "weightedWagered": 5869.491113481965
  },
  {
    "rank": 10,
    "uid": "b6ea05f7-28b2-4c81-8adc-8afce3b53c64",
    "username": "F1Fan1997",
    "wagered": 4292.813068519442,
    "weightedWagered": 3933.118724515462
  }
]