{
  "leaderboard_type": "weekly_multiplier",
  "period": {
    "start_date": "2026-07-10T00:00:00+00:00",
    "end_date": "2026-07-16T23:59:59.999999+00:00",
    "start_timestamp": 1783641600,
    "end_timestamp": 1784246399
  },
  "last_updated": "2026-07-10T03:29:22.401051+00:00",
  "last_updated_timestamp": 1783654162,
  "entries": [
    {
      "rank": 1,
      "username": "F1Fan1997",
      "multiplier": 2.5,
      "game": "Blackjack",
      "game_identifier": null,
      "wagered": 0.359877218346,
      "payout": 0.899693045865,
      "prize": 25
    },
    {
      "rank": 2,
      "username": "Alxxwilson",
      "multiplier": 2.0666666666666664,
      "game": "Merge Up 2",
      "game_identifier": null,
      "wagered": 0.21173057988000002,
      "payout": 0.437576531752,
      "prize": 15
    },
    {
      "rank": 3,
      "username": "slicksloth97",
      "multiplier": 2,
      "game": "Blackjack",
      "game_identifier": null,
      "wagered": 0.52270407529,
      "payout": 1.04540815058,
      "prize": 10
    }
  ]
}