[
  {
    "rank": 1,
    "uid": "ee7092eb-12c5-4187-89c2-6a970abe4647",
    "username": "MacMacman",
    "wagered": 230573.79999999818,
    "weightedWagered": 199990.7999999977
  },
  {
    "rank": 2,
    "uid": "d0d74e0f-6c75-4d74-a7cd-4d0a60dac400",
    "username": "Zopipa",
    "wagered": 72431.93000004788,
    "weightedWagered": 58544.630000041216
  },
  {
    "rank": 3,
    "uid": "d57ed2f5-814a-42cd-b347-0675b4dc3dcd",
    "username": "slicksloth97",
    "wagered": 119185.49438682482,
    "weightedWagered": 54320.75813852081
  },
  {
    "rank": 4,
    "uid": "a4fd519d-4cb0-478c-b08f-d062a6755b15",
    "username": "fliptheswitchop",
    "wagered": 75857.07320865757,
    "weightedWagered": 42778.477909594665
  },
  {
    "rank": 5,
    "uid": "16a098a3-be65-45a4-bcb5-72716ba74664",
    "username": "Gabtoupin",
    "wagered": 40570.478737801735,
    "weightedWagered": 40431.61639746133
  },
  {
    "rank": 6,
    "uid": "b90bde1d-5c60-45af-930b-d2d1f15cc1a6",
    "username": "smithloic2",
    "wagered": 34464.102699621304,
    "weightedWagered": 33458.70285212065
  },
  {
    "rank": 7,
    "uid": "8f79fff3-052e-4692-9d4f-ae3a36931d21",
    "username": "Jameskobi10",
    "wagered": 24509.987769922165,
    "weightedWagered": 23337.28255409118
  },
  {
    "rank": 8,
    "uid": "b6ea05f7-28b2-4c81-8adc-8afce3b53c64",
    "username": "F1Fan1997",
    "wagered": 23349.40724669543,
    "weightedWagered": 19777.04357067077
  },
  {
    "rank": 9,
    "uid": "0dbf266b-1680-4057-86be-22ac6470842e",
    "username": "hotrunners",
    "wagered": 20253.940000009115,
    "weightedWagered": 15970.40000000549
  },
  {
    "rank": 10,
    "uid": "4c3b9e0e-cbed-48b6-9286-414dbe49ddd2",
    "username": "tremor11",
    "wagered": 18319.40586544802,
    "weightedWagered": 13879.34858141799
  }
]