[
  {
    "rank": 1,
    "uid": "9639491d-3e54-47fa-a116-0294790dbe9a",
    "username": "Foxxy123",
    "wagered": 105661.24804934456,
    "weightedWagered": 102577.09241405436
  },
  {
    "rank": 2,
    "uid": "0dbf266b-1680-4057-86be-22ac6470842e",
    "username": "hotrunners",
    "wagered": 52222.806953156156,
    "weightedWagered": 47908.88695315559
  },
  {
    "rank": 3,
    "uid": "16a098a3-be65-45a4-bcb5-72716ba74664",
    "username": "Gabtoupin",
    "wagered": 24192.432314117283,
    "weightedWagered": 24186.612159432265
  },
  {
    "rank": 4,
    "uid": "d57ed2f5-814a-42cd-b347-0675b4dc3dcd",
    "username": "slicksloth97",
    "wagered": 23632.24479723941,
    "weightedWagered": 16177.441305732706
  },
  {
    "rank": 5,
    "uid": "8f79fff3-052e-4692-9d4f-ae3a36931d21",
    "username": "Jameskobi10",
    "wagered": 14925.165531900078,
    "weightedWagered": 14599.997754538941
  },
  {
    "rank": 6,
    "uid": "b6ea05f7-28b2-4c81-8adc-8afce3b53c64",
    "username": "F1Fan1997",
    "wagered": 12604.855917222192,
    "weightedWagered": 7883.036752385219
  },
  {
    "rank": 7,
    "uid": "79c0ff7b-dde8-4998-beea-4f3bb4e61c3b",
    "username": "flipmiller",
    "wagered": 7249.6670300031365,
    "weightedWagered": 6986.374248229946
  },
  {
    "rank": 8,
    "uid": "ec5371fd-0e98-40d0-897f-e389773c0684",
    "username": "Meepflips",
    "wagered": 7355.243199475481,
    "weightedWagered": 6637.971935530323
  },
  {
    "rank": 9,
    "uid": "fb2475ce-e59f-4fd1-8edb-17b3e743423e",
    "username": "WCDegen",
    "wagered": 24662.005247905934,
    "weightedWagered": 5591.066982515765
  },
  {
    "rank": 10,
    "uid": "7f921117-01a7-4d12-9605-3e33f03c14de",
    "username": "Alxxwilson",
    "wagered": 4883.372990714745,
    "weightedWagered": 4868.907099953578
  }
]