[
  {
    "rank": 1,
    "uid": "ee7092eb-12c5-4187-89c2-6a970abe4647",
    "username": "MacMacman",
    "wagered": 182402.79999997275,
    "weightedWagered": 157435.79999996736
  },
  {
    "rank": 2,
    "uid": "d57ed2f5-814a-42cd-b347-0675b4dc3dcd",
    "username": "slicksloth97",
    "wagered": 117513.5496901868,
    "weightedWagered": 53072.991583040086
  },
  {
    "rank": 3,
    "uid": "d0d74e0f-6c75-4d74-a7cd-4d0a60dac400",
    "username": "Zopipa",
    "wagered": 54695.73000003841,
    "weightedWagered": 47265.530000055456
  },
  {
    "rank": 4,
    "uid": "a4fd519d-4cb0-478c-b08f-d062a6755b15",
    "username": "fliptheswitchop",
    "wagered": 66818.78617694034,
    "weightedWagered": 38803.93151966571
  },
  {
    "rank": 5,
    "uid": "16a098a3-be65-45a4-bcb5-72716ba74664",
    "username": "Gabtoupin",
    "wagered": 38600.2713700223,
    "weightedWagered": 38461.4090296819
  },
  {
    "rank": 6,
    "uid": "b90bde1d-5c60-45af-930b-d2d1f15cc1a6",
    "username": "smithloic2",
    "wagered": 31892.071579152846,
    "weightedWagered": 30886.671731652033
  },
  {
    "rank": 7,
    "uid": "8f79fff3-052e-4692-9d4f-ae3a36931d21",
    "username": "Jameskobi10",
    "wagered": 24344.63649631315,
    "weightedWagered": 23320.747426730577
  },
  {
    "rank": 8,
    "uid": "b6ea05f7-28b2-4c81-8adc-8afce3b53c64",
    "username": "F1Fan1997",
    "wagered": 23163.585691003922,
    "weightedWagered": 19671.267588061357
  },
  {
    "rank": 9,
    "uid": "0dbf266b-1680-4057-86be-22ac6470842e",
    "username": "hotrunners",
    "wagered": 20247.34000000644,
    "weightedWagered": 15963.80000000315
  },
  {
    "rank": 10,
    "uid": "4c3b9e0e-cbed-48b6-9286-414dbe49ddd2",
    "username": "tremor11",
    "wagered": 16325.063160851863,
    "weightedWagered": 12171.920013346176
  }
]