[
  {
    "rank": 1,
    "uid": "9ed55e72-3faa-4fbe-bf35-1291fb365c07",
    "username": "MrBrizz",
    "wagered": 1382.3267706999936,
    "weightedWagered": 1336.6686696700044
  },
  {
    "rank": 2,
    "uid": "ee7092eb-12c5-4187-89c2-6a970abe4647",
    "username": "MacMacman",
    "wagered": 1221.9999999999768,
    "weightedWagered": 1221.9999999999768
  },
  {
    "rank": 3,
    "uid": "54ba7542-df9e-486e-9491-3c3e124875c1",
    "username": "gdigital87",
    "wagered": 284.2199999999999,
    "weightedWagered": 284.2199999999999
  },
  {
    "rank": 4,
    "uid": "68465667-21bf-4cd7-b674-dce075b60755",
    "username": "Laztheraz",
    "wagered": 194.45999999999972,
    "weightedWagered": 194.45999999999972
  },
  {
    "rank": 5,
    "uid": "8ec037ae-a2b4-4266-8239-c31d9c95ef04",
    "username": "WhiteRabbit420",
    "wagered": 4943.403652000359,
    "weightedWagered": 153.17463999999654
  },
  {
    "rank": 6,
    "uid": "5b5101c6-5fac-4945-9818-9edce46057a3",
    "username": "jonnyb12345",
    "wagered": 85.05067420000019,
    "weightedWagered": 85.05067420000019
  },
  {
    "rank": 7,
    "uid": "b6ea05f7-28b2-4c81-8adc-8afce3b53c64",
    "username": "F1Fan1997",
    "wagered": 100.1216353999994,
    "weightedWagered": 82.51605553999995
  },
  {
    "rank": 8,
    "uid": "16a098a3-be65-45a4-bcb5-72716ba74664",
    "username": "Gabtoupin",
    "wagered": 69.70638900000003,
    "weightedWagered": 69.70638900000003
  },
  {
    "rank": 9,
    "uid": "bb392ccd-3ef8-43b7-adc2-28687b06519c",
    "username": "Deg4Flip",
    "wagered": 1.5631812000000005,
    "weightedWagered": 1.5631812000000005
  }
]