[
  {
    "rank": 1,
    "uid": "ee7092eb-12c5-4187-89c2-6a970abe4647",
    "username": "MacMacman",
    "wagered": 175343.20000000042,
    "weightedWagered": 150733.70000000042
  },
  {
    "rank": 2,
    "uid": "d57ed2f5-814a-42cd-b347-0675b4dc3dcd",
    "username": "slicksloth97",
    "wagered": 114700.65280260591,
    "weightedWagered": 51489.52323473861
  },
  {
    "rank": 3,
    "uid": "d0d74e0f-6c75-4d74-a7cd-4d0a60dac400",
    "username": "Zopipa",
    "wagered": 35478.13000000424,
    "weightedWagered": 32823.72999999664
  },
  {
    "rank": 4,
    "uid": "a4fd519d-4cb0-478c-b08f-d062a6755b15",
    "username": "fliptheswitchop",
    "wagered": 48531.82414866483,
    "weightedWagered": 30892.82710787796
  },
  {
    "rank": 5,
    "uid": "16a098a3-be65-45a4-bcb5-72716ba74664",
    "username": "Gabtoupin",
    "wagered": 27432.392788397778,
    "weightedWagered": 27375.91975397456
  },
  {
    "rank": 6,
    "uid": "b90bde1d-5c60-45af-930b-d2d1f15cc1a6",
    "username": "smithloic2",
    "wagered": 19584.840435456867,
    "weightedWagered": 18616.111268847028
  },
  {
    "rank": 7,
    "uid": "b6ea05f7-28b2-4c81-8adc-8afce3b53c64",
    "username": "F1Fan1997",
    "wagered": 22058.597314316718,
    "weightedWagered": 18606.537626271038
  },
  {
    "rank": 8,
    "uid": "0dbf266b-1680-4057-86be-22ac6470842e",
    "username": "hotrunners",
    "wagered": 20179.93999999714,
    "weightedWagered": 15896.399999997993
  },
  {
    "rank": 9,
    "uid": "8f79fff3-052e-4692-9d4f-ae3a36931d21",
    "username": "Jameskobi10",
    "wagered": 14121.747584454151,
    "weightedWagered": 13213.775908169227
  },
  {
    "rank": 10,
    "uid": "4c3b9e0e-cbed-48b6-9286-414dbe49ddd2",
    "username": "tremor11",
    "wagered": 12848.530105053804,
    "weightedWagered": 9456.617060002003
  }
]