[
  {
    "rank": 1,
    "uid": "ee7092eb-12c5-4187-89c2-6a970abe4647",
    "username": "MacMacman",
    "wagered": 104176.8000000009,
    "weightedWagered": 82120.80000000041
  },
  {
    "rank": 2,
    "uid": "d57ed2f5-814a-42cd-b347-0675b4dc3dcd",
    "username": "slicksloth97",
    "wagered": 77543.82000000104,
    "weightedWagered": 35172.22699999961
  },
  {
    "rank": 3,
    "uid": "d0d74e0f-6c75-4d74-a7cd-4d0a60dac400",
    "username": "Zopipa",
    "wagered": 26071.33000001051,
    "weightedWagered": 24748.930000001525
  },
  {
    "rank": 4,
    "uid": "a4fd519d-4cb0-478c-b08f-d062a6755b15",
    "username": "fliptheswitchop",
    "wagered": 30362.59725525961,
    "weightedWagered": 23758.66917968559
  },
  {
    "rank": 5,
    "uid": "16a098a3-be65-45a4-bcb5-72716ba74664",
    "username": "Gabtoupin",
    "wagered": 22235.05250786588,
    "weightedWagered": 22178.579473442685
  },
  {
    "rank": 6,
    "uid": "b6ea05f7-28b2-4c81-8adc-8afce3b53c64",
    "username": "F1Fan1997",
    "wagered": 20173.60100844816,
    "weightedWagered": 16867.841196812675
  },
  {
    "rank": 7,
    "uid": "b90bde1d-5c60-45af-930b-d2d1f15cc1a6",
    "username": "smithloic2",
    "wagered": 12003.853263588755,
    "weightedWagered": 11294.381260195483
  },
  {
    "rank": 8,
    "uid": "0dbf266b-1680-4057-86be-22ac6470842e",
    "username": "hotrunners",
    "wagered": 13074.800000005383,
    "weightedWagered": 9096.800000002053
  },
  {
    "rank": 9,
    "uid": "8f79fff3-052e-4692-9d4f-ae3a36931d21",
    "username": "Jameskobi10",
    "wagered": 8597.481227307804,
    "weightedWagered": 8503.195074953608
  },
  {
    "rank": 10,
    "uid": "4c3b9e0e-cbed-48b6-9286-414dbe49ddd2",
    "username": "tremor11",
    "wagered": 10619.860544304534,
    "weightedWagered": 7278.369237195061
  }
]